spotify/_spotify_build.py
spotify/link.py
spotify/user.py
spotify/social.py
spotify/config.py
spotify/version.py
spotify/compat.py
spotify/error.py
spotify/sink.py
spotify/track.py
spotify/_spotify.so
spotify/playlist_unseen_tracks.py
spotify/session.py
spotify/__init__.py
spotify/offline.py
spotify/eventloop.py
spotify/album.py
spotify/artist.py
spotify/api.h
spotify/connection.py
spotify/playlist_track.py
spotify/playlist_container.py
spotify/utils.py
spotify/player.py
spotify/playlist.py
spotify/api.processed.h
spotify/inbox.py
spotify/search.py
spotify/audio.py
spotify/toplist.py
spotify/image.py
spotify/.dylibs/libspotify.12.1.51.dylib
pyspotify-2.1.3.dist-info/RECORD
pyspotify-2.1.3.dist-info/LICENSE
pyspotify-2.1.3.dist-info/WHEEL
pyspotify-2.1.3.dist-info/top_level.txt
pyspotify-2.1.3.dist-info/METADATA
