Metadata-Version: 2.1
Name: pyspotify
Version: 2.1.3
Summary: Python wrapper for libspotify
Home-page: https://pyspotify.readthedocs.io/
Author: Stein Magnus Jodal
Author-email: stein.magnus@jodal.no
License: Apache License, Version 2.0
Platform: UNKNOWN
Classifier: Development Status :: 5 - Production/Stable
Classifier: Intended Audience :: Developers
Classifier: License :: OSI Approved :: Apache Software License
Classifier: Programming Language :: Python :: 2
Classifier: Programming Language :: Python :: 2.7
Classifier: Programming Language :: Python :: 3
Classifier: Programming Language :: Python :: 3.5
Classifier: Programming Language :: Python :: 3.6
Classifier: Programming Language :: Python :: 3.7
Classifier: Programming Language :: Python :: 3.8
Classifier: Programming Language :: Python :: Implementation :: CPython
Classifier: Programming Language :: Python :: Implementation :: PyPy
Classifier: Topic :: Software Development :: Libraries
Provides-Extra: docs
Provides-Extra: test
Provides-Extra: release
Provides-Extra: lint
Provides-Extra: dev
